xmacis2py/__init__.py
xmacis2py/analysis_tools/__init__.py
xmacis2py/analysis_tools/analysis.py
xmacis2py/data_access/__init__.py
xmacis2py/data_access/get_data.py
xmacis2py/graphics/__init__.py
xmacis2py/graphics/precipitation.py
xmacis2py/graphics/temperature.py
xmacis2py/utils/__init__.py
xmacis2py/utils/file_funcs.py
xmacis2py-2.0.dist-info/licenses/LICENSE
xmacis2py-2.0.dist-info/METADATA
xmacis2py-2.0.dist-info/WHEEL
xmacis2py-2.0.dist-info/top_level.txt
xmacis2py-2.0.dist-info/RECORD
