Metadata-Version: 2.4
Name: xmacis2py
Version: 2.0
Summary: A Python library that downloads data from the Applied Climate Information System (ACIS) Database, performs various types of analyses on the data and makes various types of graphical summaries of the data.
Author: Eric J. Drewitz
Keywords: meteorology,atmospheric sciences
Classifier: Programming Language :: Python
Classifier: Topic :: Scientific/Engineering
Classifier: Topic :: Scientific/Engineering :: Atmospheric Science
Classifier: Operating System :: OS Independent
Requires-Python: >=3.10
License-File: LICENSE
Requires-Dist: matplotlib>=3.7
Requires-Dist: wxdata>=1.2.3
Dynamic: license-file
